{"is_source_file": true, "format": "JavaScript", "description": "This file defines a UI component named 'Card' using the LightningJS framework and Blits library. The component displays a surface with a title and body text, configurable through properties.", "external_files": ["@lightningjs/blits", "../theme.js"], "external_methods": [], "published": ["Card"], "classes": [], "methods": [{"name": "state", "description": "Initializes component state variables such as dimensions, colors, and text content."}, {"name": "onInit", "description": "Sets the component state based on the provided properties during initialization."}], "calls": ["this.$state.w", "this.$state.h", "this.$state.titleText", "this.$state.bodyText"], "search-terms": ["Card", "LightningJS component", "Props", "Template", "state()", "onInit()", "title", "body", "ui component"], "state": 2, "file_id": 42, "knowledge_revision": 140, "git_revision": "4fb28c6d060caffa45081beca534aeef9d494b84", "revision_history": [{"85": ""}, {"96": ""}, {"111": "14bf8f709fd4611da0cc27979a6fd7ef3616db49"}, {"114": "14bf8f709fd4611da0cc27979a6fd7ef3616db49"}, {"120": "4fb28c6d060caffa45081beca534aeef9d494b84"}, {"133": "4fb28c6d060caffa45081beca534aeef9d494b84"}, {"140": "4fb28c6d060caffa45081beca534aeef9d494b84"}], "ctags": [], "hash": "e83a906d7a6d0fd6cb96ac48418221f7", "format-version": 4, "code-base-name": "quiz_app_frontend", "filename": "quiz_app_frontend/src/components/Card.js"}