{"is_source_file": true, "format": "JavaScript", "description": "This file defines a 'Results' component for a Lightning.js-based quiz application frontend. It includes UI layout, state management, and input handling for displaying quiz results and restart options.", "external_files": ["@lightningjs/blits", "../theme.js", "../components/Card.js"], "external_methods": ["$router.to"], "published": [], "classes": [{"name": "Results", "description": "A Lightning.js component representing the results page, including score display and navigation controls."}], "methods": [{"name": "scoreText", "description": "Computed property to generate the display string for the user's score."}, {"name": "ready", "description": "Lifecycle hook that initializes the component state by parsing URL query parameters and resets the quiz score in local storage."}, {"name": "up", "description": "Input handler to focus the restart button when the Up key is pressed."}, {"name": "down", "description": "Input handler to focus the restart button when the Down key is pressed."}, {"name": "enter", "description": "Input handler that navigates to the quiz page when Enter is pressed."}, {"name": "back", "description": "Input handler that navigates to the home page when back action is triggered."}], "calls": ["$router.to('/quiz')", "$router.to('/')"], "search-terms": ["Results component", "Lightning.js Results", "quiz results display", "score parsing", "navigation handlers", "Results.js", "Results page layout"], "state": 2, "file_id": 45, "knowledge_revision": 97, "git_revision": "", "revision_history": [{"92": ""}, {"97": ""}], "ctags": [], "hash": "a45577bdf023d5c9751d30ae52271c4d", "format-version": 4, "code-base-name": "quiz_app_frontend", "filename": "quiz_app_frontend/src/pages/Results.js"}